setup.py
Leono_dist/Binomialdistribution.py
Leono_dist/Gaussiandistribution.py
Leono_dist/Generaldistribution.py
Leono_dist/__init__.py
Leono_dist.egg-info/PKG-INFO
Leono_dist.egg-info/SOURCES.txt
Leono_dist.egg-info/dependency_links.txt
Leono_dist.egg-info/not-zip-safe
Leono_dist.egg-info/top_level.txt