Metadata-Version: 1.0
Name: Leono-dist
Version: 0.1
Summary: Gaussian and Binomial distributions
Home-page: UNKNOWN
Author: Leonardo Becerra
Author-email: UNKNOWN
License: UNKNOWN
Platform: UNKNOWN
